Shutter/Shutter.py
Shutter/__init__.py
Shutter_GSJiang66-0.0.4.dist-info/LICENSE.txt
Shutter_GSJiang66-0.0.4.dist-info/METADATA
Shutter_GSJiang66-0.0.4.dist-info/WHEEL
Shutter_GSJiang66-0.0.4.dist-info/top_level.txt
Shutter_GSJiang66-0.0.4.dist-info/RECORD
